LICENSE.md
MANIFEST.in
README.md
build_upload.md
pyproject.toml
setup.cfg
setup.py
src/selenium_injector/__init__.py
src/selenium_injector/webdriver.py
src/selenium_injector.egg-info/PKG-INFO
src/selenium_injector.egg-info/SOURCES.txt
src/selenium_injector.egg-info/dependency_links.txt
src/selenium_injector.egg-info/requires.txt
src/selenium_injector.egg-info/top_level.txt
src/selenium_injector/files/extension/background.js
src/selenium_injector/files/extension/manifest_2.json
src/selenium_injector/files/extension/manifest_3.json
src/selenium_injector/files/extension/stay_alive.js
src/selenium_injector/files/js/connection.js
src/selenium_injector/files/js/returner.js
src/selenium_injector/scripts/__init__.py
src/selenium_injector/scripts/injector.py
src/selenium_injector/scripts/socket.py
src/selenium_injector/scripts/sync_websocket.py
src/selenium_injector/types/__init__.py
src/selenium_injector/types/by.py
src/selenium_injector/types/js.py
src/selenium_injector/types/webelement.py
src/selenium_injector/utils/__init__.py
src/selenium_injector/utils/utils.py